{
	"info": {
		"_postman_id": "76244059-5ac8-4038-b088-c609d7dff312",
		"name": "Student API Collection",
		"schema": "https://schema.getpostman.com/json/collection/v2.1.0/collection.json",
		"_exporter_id": "20538504",
		"_collection_link": "https://warped-capsule-624251.postman.co/workspace/My-Workspace~9d832946-1443-490b-8be6-f780154825f9/collection/20538504-76244059-5ac8-4038-b088-c609d7dff312?action=share&source=collection_link&creator=20538504"
	},
	"item": [
		{
			"name": "Create Student",
			"request": {
				"method": "POST",
				"header": [
					{
						"key": "Content-Type",
						"value": "application/json"
					}
				],
				"body": {
					"mode": "raw",
					"raw": "{\n    \"name\": \"Alice\",\n    \"email\": \"alice@example.com\",\n    \"phone\": \"1234567890\"\n}"
				},
				"url": {
					"raw": "http://localhost:3000/api/students",
					"protocol": "http",
					"host": [
						"localhost"
					],
					"port": "3000",
					"path": [
						"api",
						"students"
					]
				}
			},
			"response": []
		},
		{
			"name": "Get All Students (Paginated)",
			"request": {
				"method": "GET",
				"header": [],
				"url": {
					"raw": "http://localhost:3000/api/students?page=1&limit=5",
					"protocol": "http",
					"host": [
						"localhost"
					],
					"port": "3000",
					"path": [
						"api",
						"students"
					],
					"query": [
						{
							"key": "page",
							"value": "1"
						},
						{
							"key": "limit",
							"value": "5"
						}
					]
				}
			},
			"response": []
		},
		{
			"name": "Get Single Student by ID",
			"request": {
				"method": "GET",
				"header": [],
				"url": {
					"raw": "http://localhost:3000/api/students/1",
					"protocol": "http",
					"host": [
						"localhost"
					],
					"port": "3000",
					"path": [
						"api",
						"students",
						"1"
					]
				}
			},
			"response": []
		},
		{
			"name": "Update Student",
			"request": {
				"method": "PUT",
				"header": [
					{
						"key": "Content-Type",
						"value": "application/json"
					}
				],
				"body": {
					"mode": "raw",
					"raw": "{\n    \"name\": \"Alice Updated\",\n    \"email\": \"alice_updated@example.com\",\n    \"phone\": \"9876543210\"\n}"
				},
				"url": {
					"raw": "http://localhost:3000/api/students/1",
					"protocol": "http",
					"host": [
						"localhost"
					],
					"port": "3000",
					"path": [
						"api",
						"students",
						"1"
					]
				}
			},
			"response": []
		},
		{
			"name": "Delete Student",
			"request": {
				"method": "DELETE",
				"header": [],
				"url": {
					"raw": "http://localhost:3000/api/students/1",
					"protocol": "http",
					"host": [
						"localhost"
					],
					"port": "3000",
					"path": [
						"api",
						"students",
						"1"
					]
				}
			},
			"response": []
		}
	]
}